LICENSE
MANIFEST.in
README.rst
setup.py
django_atomic_dispatch/__init__.py
django_atomic_dispatch.egg-info/PKG-INFO
django_atomic_dispatch.egg-info/SOURCES.txt
django_atomic_dispatch.egg-info/dependency_links.txt
django_atomic_dispatch.egg-info/top_level.txt
django_atomic_dispatch.egg-info/zip-safe