Metadata-Version: 1.1
Name: django-atomic-dispatch
Version: 2.0.0
Summary: Atomic transaction aware signals for Django 1.6+
Home-page: https://github.com/adamchainz/django_atomic_dispatch
Author: Adam Johnson
Author-email: me@adamj.eu
License: Copyright (c) Nick Bruun <nick@bruun.co>
